setup.py
mongopy/__init__.py
mongopy.egg-info/PKG-INFO
mongopy.egg-info/SOURCES.txt
mongopy.egg-info/dependency_links.txt
mongopy.egg-info/requires.txt
mongopy.egg-info/top_level.txt
test/test_benchmark.py
test/test_mongopy.py