Metadata-Version: 1.0
Name: mongopy
Version: 0.01
Summary: schemaless python memory store
Home-page: https://github.com/jarrodb/mongopy
Author: Jarrod Baumann
Author-email: jarrod@ipglobal.net
License: http://www.apache.org/licenses/LICENSE-2.0
Platform: UNKNOWN
